magdi_segmentation_models_3d/__init__.py
magdi_segmentation_models_3d/swinunetrv2/__init__.py
magdi_segmentation_models_3d/swinunetrv2/configuration_swinunetr2.py
magdi_segmentation_models_3d/swinunetrv2/image_processing_swinunetrv2.py
magdi_segmentation_models_3d/swinunetrv2/modeling_swinunetrv2.py
magdi_segmentation_models_3d/swinunetrv2/registration_swinunetrv2.py
magdi_segmentation_models_3d/unet/__init__.py
magdi_segmentation_models_3d/unet/configuration_unet.py
magdi_segmentation_models_3d/unet/image_processing_unet.py
magdi_segmentation_models_3d/unet/modeling_unet.py
magdi_segmentation_models_3d/unet/registration_unet.py
magdi_segmentation_models_3d-0.0.0.dist-info/METADATA
magdi_segmentation_models_3d-0.0.0.dist-info/WHEEL
magdi_segmentation_models_3d-0.0.0.dist-info/top_level.txt
magdi_segmentation_models_3d-0.0.0.dist-info/RECORD
